awardwallet/__init__.py
awardwallet/__main__.py
awardwallet/_version.py
awardwallet/client.py
awardwallet/model.py
awardwallet-0.2.0.dist-info/licenses/LICENSE
awardwallet-0.2.0.dist-info/METADATA
awardwallet-0.2.0.dist-info/WHEEL
awardwallet-0.2.0.dist-info/entry_points.txt
awardwallet-0.2.0.dist-info/top_level.txt
awardwallet-0.2.0.dist-info/RECORD
